[{"school":"Auburn University","unit":"Central","name":"Will Johnson","title":"Assistant Vice President for Philanthropy","email":"wjohnson@auburn.edu","phone":"334-844-1139","focus":"Oversees college development incl. health-science","src":"auburngiving.org","email_status":"guessed","decile":8,"sent":"","replied":"","bounced":"","meeting":"","ostatus":"Not contacted"},{"school":"Auburn University","unit":"Central","name":"Alesia Davenport","title":"Senior Director of Planned Giving","email":"plannedgiving@auburn.edu","phone":"334-844-7375","focus":"Planned giving","src":"auburngiving.org","email_status":"confirmed","decile":8,"sent":"","replied":"","bounced":"","meeting":"","ostatus":"Not contacted"},{"school":"The University of Central Florida Board of Trustees","unit":"Engineering","name":"Mike Worley","title":"Executive Director of Development, College of Engineering & Computer Science","email":"michael.worley@ucf.edu","phone":"","focus":"Development lead – Engineering & Computer Science","src":"advance.ucf.edu","email_status":"confirmed","decile":8,"sent":"","replied":"","bounced":"","meeting":"","ostatus":"Not contacted"},{"school":"The University of Central Florida Board of Trustees","unit":"Engineering","name":"Jane Stump","title":"Associate Director of Development, Engineering & Optics/Photonics","email":"jane.stump@ucf.edu","phone":"407-882-1268","focus":"Major gifts – Engineering & Optics","src":"advance.ucf.edu","email_status":"confirmed","decile":8,"sent":"","replied":"","bounced":"","meeting":"","ostatus":"Not contacted"},{"school":"The University of Central Florida Board of Trustees","unit":"Medicine","name":"Katie Korkosz","title":"Executive Director of Advancement, Health Affairs","email":"katiek@ucf.edu","phone":"407-823-1600","focus":"Development lead – Medicine / Nursing (Health Affairs)","src":"advance.ucf.edu","email_status":"confirmed","decile":8,"sent":"","replied":"","bounced":"","meeting":"","ostatus":"Not contacted"},{"school":"The University of Central Florida Board of Trustees","unit":"Medicine","name":"Thomas Bolick","title":"Senior Director of Development, College of Medicine","email":"thomas.bolick@ucf.edu","phone":"407-823-0125","focus":"Major gifts – College of Medicine","src":"advance.ucf.edu","email_status":"confirmed","decile":8,"sent":"","replied":"","bounced":"","meeting":"","ostatus":"Not contacted"},{"school":"The University of Central Florida Board of Trustees","unit":"Medicine","name":"Carla Craig","title":"Director for Development, College of Nursing","email":"carla.craig@ucf.edu","phone":"407-823-0712","focus":"Major gifts – Nursing","src":"advance.ucf.edu","email_status":"confirmed","decile":8,"sent":"","replied":"","bounced":"","meeting":"","ostatus":"Not contacted"},{"school":"The University of Central Florida Board of Trustees","unit":"Science","name":"Christina Starace","title":"Executive Director of Development, College of Sciences","email":"christina.starace@ucf.edu","phone":"407-823-1978","focus":"Development lead – College of Sciences","src":"advance.ucf.edu","email_status":"confirmed","decile":8,"sent":"","replied":"","bounced":"","meeting":"","ostatus":"Not contacted"},{"school":"The University of Central Florida Board of Trustees","unit":"Science","name":"Chelsea Dalager","title":"Director of Development, College of Sciences","email":"chelsea.dalager@ucf.edu","phone":"407-823-0066","focus":"Major gifts – Sciences","src":"advance.ucf.edu","email_status":"confirmed","decile":8,"sent":"","replied":"","bounced":"","meeting":"","ostatus":"Not contacted"},{"school":"The University of Central Florida Board of Trustees","unit":"Central","name":"Anthony Pomonis","title":"Assistant Vice President, Transformational Giving","email":"anthony.pomonis@ucf.edu","phone":"407-882-0319","focus":"Principal/leadership gifts","src":"advance.ucf.edu","email_status":"confirmed","decile":8,"sent":"","replied":"","bounced":"","meeting":"","ostatus":"Not contacted"},{"school":"The University of Central Florida Board of Trustees","unit":"Central","name":"Chris Lambert","title":"Assistant Vice President, Planned Giving & Regional Programs","email":"chris.lambert@ucf.edu","phone":"407-882-0292","focus":"Planned giving","src":"advance.ucf.edu","email_status":"confirmed","decile":8,"sent":"","replied":"","bounced":"","meeting":"","ostatus":"Not contacted"},{"school":"University of Texas at Arlington","unit":"Engineering","name":"Myrshem George","title":"Assistant Dean of Development, College of Engineering","email":"myrshem.george@uta.edu","phone":"817-272-6163","focus":"Development lead – Engineering","src":"uta.edu","email_status":"confirmed","decile":8,"sent":"","replied":"","bounced":"","meeting":"","ostatus":"Not contacted"},{"school":"University of Texas at Arlington","unit":"Engineering","name":"Adrian Bautista","title":"Director of Development, College of Engineering","email":"adrian.bautista@uta.edu","phone":"817-272-8535","focus":"Major gifts – Engineering","src":"uta.edu","email_status":"confirmed","decile":8,"sent":"","replied":"","bounced":"","meeting":"","ostatus":"Not contacted"},{"school":"University of Texas at Arlington","unit":"Medicine","name":"Lauren Bayans","title":"Director of Development, College of Nursing & Health Innovation","email":"lauren.bayans@uta.edu","phone":"817-272-2938","focus":"Major gifts – Nursing & Health Innovation","src":"uta.edu","email_status":"confirmed","decile":8,"sent":"","replied":"","bounced":"","meeting":"","ostatus":"Not contacted"},{"school":"University of Texas at Arlington","unit":"Science","name":"Trey Smith","title":"Director of Development, College of Science","email":"trey.smith@uta.edu","phone":"817-272-2145","focus":"Major gifts – College of Science","src":"uta.edu","email_status":"confirmed","decile":8,"sent":"","replied":"","bounced":"","meeting":"","ostatus":"Not contacted"},{"school":"University of Texas at Arlington","unit":"Central","name":"Marie Schultz","title":"Vice President, Development & Alumni Relations","email":"marie.schultz@uta.edu","phone":"817-272-2584","focus":"Chief development officer","src":"uta.edu","email_status":"confirmed","decile":8,"sent":"","replied":"","bounced":"","meeting":"","ostatus":"Not contacted"},{"school":"University of Texas at Arlington","unit":"Central","name":"Rose Youngblood","title":"AVP, Development & Principal Gifts","email":"rose.youngblood@uta.edu","phone":"817-272-6851","focus":"Principal/major gifts","src":"uta.edu","email_status":"confirmed","decile":8,"sent":"","replied":"","bounced":"","meeting":"","ostatus":"Not contacted"},{"school":"University of Texas at Arlington","unit":"Central","name":"LaRence Snowden","title":"AVP, Corporate & Foundation Engagement","email":"larence.snowden@uta.edu","phone":"817-272-4321","focus":"Corporate & foundation relations","src":"uta.edu","email_status":"confirmed","decile":8,"sent":"","replied":"","bounced":"","meeting":"","ostatus":"Not contacted"},{"school":"University of Texas at Arlington","unit":"Central","name":"Ward Sullivan","title":"Senior Director, Gift Planning","email":"ward.sullivan@uta.edu","phone":"817-272-1042","focus":"Planned giving","src":"uta.edu","email_status":"confirmed","decile":8,"sent":"","replied":"","bounced":"","meeting":"","ostatus":"Not contacted"},{"school":"Dartmouth College","unit":"Engineering","name":"Mark Dorgan","title":"Executive Director of Advancement, Thayer School of Engineering","email":"mark.w.dorgan@dartmouth.edu","phone":"603-646-1867","focus":"Development lead – Engineering","src":"engineering.dartmouth.edu","email_status":"confirmed","decile":8,"sent":"","replied":"","bounced":"","meeting":"","ostatus":"Not contacted"},{"school":"Dartmouth College","unit":"Engineering","name":"Will Chambers","title":"Development Officer, Thayer Engineering","email":"william.a.chambers@dartmouth.edu","phone":"603-646-6550","focus":"Major/leadership gifts – Engineering","src":"engineering.dartmouth.edu","email_status":"confirmed","decile":8,"sent":"","replied":"","bounced":"","meeting":"","ostatus":"Not contacted"},{"school":"Dartmouth College","unit":"Medicine","name":"Matthew P. Haag","title":"CDO, Dartmouth Health; VP of Development, Geisel School of Medicine","email":"matthew.p.haag@hitchcock.org","phone":"603-646-5130","focus":"Development lead – Geisel Medicine / Dartmouth Health","src":"dhgeiselgiving.org","email_status":"confirmed","decile":8,"sent":"","replied":"","bounced":"","meeting":"","ostatus":"Not contacted"},{"school":"Dartmouth College","unit":"Medicine","name":"Kimberlee A. Labonte","title":"Executive Director of Development, Geisel School of Medicine","email":"kimberlee.a.labonte@hitchcock.org","phone":"603-646-5110","focus":"Major gifts – Geisel Medicine","src":"dhgeiselgiving.org","email_status":"confirmed","decile":8,"sent":"","replied":"","bounced":"","meeting":"","ostatus":"Not contacted"},{"school":"Dartmouth College","unit":"Medicine","name":"Jaclynn Rodriguez","title":"Executive Director of Development, Dartmouth Cancer Center","email":"jaclynn.rodriguez@hitchcock.org","phone":"603-646-5287","focus":"Major gifts – cancer","src":"dhgeiselgiving.org","email_status":"confirmed","decile":8,"sent":"","replied":"","bounced":"","meeting":"","ostatus":"Not contacted"},{"school":"Dartmouth College","unit":"Medicine","name":"Kathy M. Hubbard","title":"Director, Corporate & Foundation Relations (Dartmouth Health)","email":"kathleen.m.hubbard@hitchcock.org","phone":"603-646-5321","focus":"Corporate & foundation relations – Medicine","src":"dhgeiselgiving.org","email_status":"confirmed","decile":8,"sent":"","replied":"","bounced":"","meeting":"","ostatus":"Not contacted"},{"school":"Dartmouth College","unit":"Science","name":"Kathryn Munro","title":"Associate Vice President, Arts & Sciences Development","email":"kathryn.munro@dartmouth.edu","phone":"","focus":"Development lead – Arts & Sciences (incl. sciences)","src":"alumni.dartmouth.edu","email_status":"guessed","decile":8,"sent":"","replied":"","bounced":"","meeting":"","ostatus":"Not contacted"},{"school":"Dartmouth College","unit":"Central","name":"Matthew Rizzo","title":"Vice President for Development","email":"matthew.t.rizzo@dartmouth.edu","phone":"603-646-2221","focus":"University development leadership","src":"alumni.dartmouth.edu","email_status":"confirmed","decile":8,"sent":"","replied":"","bounced":"","meeting":"","ostatus":"Not contacted"},{"school":"Dartmouth College","unit":"Central","name":"Susan Hanifin","title":"Assistant Vice President for Gift Planning","email":"susan.e.hanifin@dartmouth.edu","phone":"603-646-3799","focus":"Planned giving","src":"alumni.dartmouth.edu","email_status":"confirmed","decile":8,"sent":"","replied":"","bounced":"","meeting":"","ostatus":"Not contacted"},{"school":"University of Pittsburgh","unit":"Engineering","name":"Cynthia Liberatore","title":"Executive Director of Development & Alumni Affairs, Swanson School of Engineering","email":"chl374@pitt.edu","phone":"412-627-7516","focus":"Development lead – Engineering","src":"engineering.pitt.edu","email_status":"confirmed","decile":8,"sent":"","replied":"","bounced":"","meeting":"","ostatus":"Not contacted"},{"school":"University of Pittsburgh","unit":"Engineering","name":"Gary Pollock","title":"Major Gifts Officer, Swanson Engineering","email":"gvp3@pitt.edu","phone":"412-624-2243","focus":"Major gifts – Engineering","src":"engineering.pitt.edu","email_status":"confirmed","decile":8,"sent":"","replied":"","bounced":"","meeting":"","ostatus":"Not contacted"},{"school":"University of Pittsburgh","unit":"Engineering","name":"RJ Rakow","title":"Director of Corporate & Foundation Relations, Engineering","email":"rjr53@pitt.edu","phone":"","focus":"Corporate & foundation relations – Engineering","src":"engineering.pitt.edu","email_status":"confirmed","decile":8,"sent":"","replied":"","bounced":"","meeting":"","ostatus":"Not contacted"},{"school":"University of Pittsburgh","unit":"Medicine","name":"Jodi Weisfield","title":"Vice Chancellor, Health Sciences & Clinical Programs Advancement","email":"jbw54@pitt.edu","phone":"412-383-0852","focus":"Development lead – Health Sciences / School of Medicine","src":"upmc.com","email_status":"confirmed","decile":8,"sent":"2026-07-16","replied":"","bounced":"","meeting":"","ostatus":"Sent"},{"school":"University of Pittsburgh","unit":"Medicine","name":"Cathy Majka","title":"Executive Director of Development, Clinical & Academic Medicine","email":"majkacl@upmc.edu","phone":"412-802-8284","focus":"Major gifts – School of Medicine","src":"upmc.com","email_status":"confirmed","decile":8,"sent":"","replied":"","bounced":"","meeting":"","ostatus":"Not contacted"},{"school":"University of Pittsburgh","unit":"Medicine","name":"Alicia King","title":"Executive Director of Development, UPMC Hillman Cancer Center","email":"kinga15@upmc.edu","phone":"412-623-4705","focus":"Development lead – cancer","src":"hillman.upmc.com","email_status":"confirmed","decile":8,"sent":"","replied":"","bounced":"","meeting":"","ostatus":"Not contacted"},{"school":"University of Pittsburgh","unit":"Science","name":"Josh Bow","title":"Executive Director of Development, Dietrich School of Arts & Sciences","email":"joshuabow@pitt.edu","phone":"412-624-3204","focus":"Development lead – Arts & Sciences (incl. sciences)","src":"as.pitt.edu","email_status":"confirmed","decile":8,"sent":"","replied":"","bounced":"","meeting":"","ostatus":"Not contacted"},{"school":"University of Pittsburgh","unit":"Science","name":"Brian Eddy","title":"Major Gifts Officer, Dietrich School of Arts & Sciences","email":"bre27@pitt.edu","phone":"412-624-8239","focus":"Major gifts – A&S sciences","src":"as.pitt.edu","email_status":"confirmed","decile":8,"sent":"","replied":"","bounced":"","meeting":"","ostatus":"Not contacted"},{"school":"University of Pittsburgh","unit":"Central","name":"Cynthia Caldwell","title":"AVC, Development & Planned Giving, Health Sciences","email":"ccaldwell@pitt.edu","phone":"412-647-0515","focus":"Health Sciences development & planned giving","src":"plannedgiving.pitt.edu","email_status":"confirmed","decile":8,"sent":"","replied":"","bounced":"","meeting":"","ostatus":"Not contacted"},{"school":"Woods Hole Oceanographic Institution","unit":"Central","name":"Samuel Harp","title":"Vice President for Advancement & Chief Marketing Officer","email":"sharp@whoi.edu","phone":"508-289-2955","focus":"Chief advancement officer","src":"whoi.edu","email_status":"confirmed","decile":8,"sent":"2026-07-16","replied":"","bounced":"","meeting":"","ostatus":"Sent"},{"school":"Woods Hole Oceanographic Institution","unit":"Central","name":"Court Clayton","title":"Chief Development Officer","email":"gclayton@whoi.edu","phone":"508-289-2545","focus":"Development / fundraising leadership","src":"whoi.edu","email_status":"confirmed","decile":8,"sent":"","replied":"","bounced":"","meeting":"","ostatus":"Not contacted"},{"school":"Woods Hole Oceanographic Institution","unit":"Science","name":"James Barnes","title":"Director of Major Gifts","email":"james.barnes@whoi.edu","phone":"508-289-3875","focus":"Major gifts – ocean science","src":"whoi.edu","email_status":"confirmed","decile":8,"sent":"","replied":"","bounced":"","meeting":"","ostatus":"Not contacted"},{"school":"Woods Hole Oceanographic Institution","unit":"Science","name":"Bridget Flynn","title":"Director of Development, Principal & Major Gifts","email":"bridget.flynn@whoi.edu","phone":"508-289-2881","focus":"Principal & major gifts – ocean science","src":"whoi.edu","email_status":"confirmed","decile":8,"sent":"","replied":"","bounced":"","meeting":"","ostatus":"Not contacted"},{"school":"Woods Hole Oceanographic Institution","unit":"Science","name":"Kimberly Benson","title":"Director of Development, Annual & Planned Giving","email":"kbenson@whoi.edu","phone":"508-289-3876","focus":"Annual & planned giving","src":"whoi.edu","email_status":"confirmed","decile":8,"sent":"","replied":"","bounced":"","meeting":"","ostatus":"Not contacted"},{"school":"Woods Hole Oceanographic Institution","unit":"Science","name":"Erika Fitzpatrick","title":"Director of Corporate & Foundation Relations","email":"efitzpatrick@whoi.edu","phone":"508-289-3281","focus":"Corporate & foundation relations","src":"whoi.edu","email_status":"confirmed","decile":8,"sent":"","replied":"","bounced":"","meeting":"","ostatus":"Not contacted"},{"school":"Woods Hole Oceanographic Institution","unit":"Science","name":"Patrick Schaefer","title":"Director of Major Gifts & Planned Giving","email":"patrick.schaefer@whoi.edu","phone":"508-289-2018","focus":"Major gifts & planned giving","src":"whoi.edu","email_status":"confirmed","decile":8,"sent":"","replied":"","bounced":"","meeting":"","ostatus":"Not contacted"},{"school":"Colorado State University","unit":"Engineering","name":"Colleen Reese","title":"Interim Executive Director of Development, Walter Scott Jr. College of Engineering","email":"colleen.reese@colostate.edu","phone":"970-491-2277","focus":"Development lead – Engineering","src":"engr.colostate.edu","email_status":"confirmed","decile":9,"sent":"","replied":"","bounced":"","meeting":"","ostatus":"Not contacted"},{"school":"Colorado State University","unit":"Engineering","name":"Aaron Rogers","title":"Associate Director of Development, Engineering","email":"aaron.rogers@colostate.edu","phone":"","focus":"Major gifts – Engineering","src":"engr.colostate.edu","email_status":"confirmed","decile":9,"sent":"","replied":"","bounced":"","meeting":"","ostatus":"Not contacted"},{"school":"Colorado State University","unit":"Engineering","name":"Drew Crouch","title":"Executive Director for Strategic Partnerships, Engineering","email":"drew.crouch@colostate.edu","phone":"970-491-2630","focus":"Corporate/industry partnerships – Engineering","src":"engr.colostate.edu","email_status":"confirmed","decile":9,"sent":"","replied":"","bounced":"","meeting":"","ostatus":"Not contacted"},{"school":"Colorado State University","unit":"Medicine","name":"Sarah Schmidt","title":"AVP for Advancement, College of Veterinary Medicine & Biomedical Sciences","email":"s.schmidt@colostate.edu","phone":"559-213-5860","focus":"Development lead – Vet Med & Biomedical Sciences","src":"vetmedbiosci.colostate.edu","email_status":"confirmed","decile":9,"sent":"","replied":"","bounced":"","meeting":"","ostatus":"Not contacted"},{"school":"Colorado State University","unit":"Medicine","name":"Marcus Palas","title":"Senior Director of Development, Vet Med & Biomedical Sciences","email":"marcus.palas@colostate.edu","phone":"970-658-7267","focus":"Major gifts – Vet Med & Biomedical Sciences","src":"vetmedbiosci.colostate.edu","email_status":"confirmed","decile":9,"sent":"","replied":"","bounced":"","meeting":"","ostatus":"Not contacted"},{"school":"Colorado State University","unit":"Medicine","name":"Torii Kapavik","title":"Senior Director of Development, Flint Animal Cancer Center","email":"torii.kapavik@colostate.edu","phone":"254-424-2327","focus":"Major gifts – comparative oncology / health","src":"vetmedbiosci.colostate.edu","email_status":"confirmed","decile":9,"sent":"","replied":"","bounced":"","meeting":"","ostatus":"Not contacted"},{"school":"Colorado State University","unit":"Medicine","name":"Katie Rothstein","title":"Director of Development, Veterinary Teaching Hospital","email":"katie.rothstein@colostate.edu","phone":"970-491-6631","focus":"Grateful-client gifts – Veterinary Teaching Hospital","src":"vetmedbiosci.colostate.edu","email_status":"confirmed","decile":9,"sent":"","replied":"","bounced":"","meeting":"","ostatus":"Not contacted"},{"school":"Colorado State University","unit":"Science","name":"Ginger Morehouse","title":"Director of Development, College of Natural Sciences","email":"ginger.morehouse@colostate.edu","phone":"970-491-5711","focus":"Development lead – Natural Sciences","src":"natsci.colostate.edu","email_status":"confirmed","decile":9,"sent":"2026-07-16","replied":"","bounced":"","meeting":"","ostatus":"Sent"},{"school":"Colorado State University","unit":"Science","name":"Rebecca Iriarte","title":"Associate Director of Development, Natural Sciences","email":"rebecca.iriarte@colostate.edu","phone":"970-491-4195","focus":"Major/annual gifts – Natural Sciences","src":"natsci.colostate.edu","email_status":"confirmed","decile":9,"sent":"","replied":"","bounced":"","meeting":"","ostatus":"Not contacted"},{"school":"Colorado State University","unit":"Science","name":"Carolyn Hove","title":"Assistant Director of Development, Natural Sciences","email":"carolyn.hove@colostate.edu","phone":"970-491-3000","focus":"Gift officer – Natural Sciences","src":"natsci.colostate.edu","email_status":"confirmed","decile":9,"sent":"","replied":"","bounced":"","meeting":"","ostatus":"Not contacted"},{"school":"Colorado State University","unit":"Central","name":"Ginny Fanning","title":"AVP, College Development, CSU Foundation","email":"Virginia.Fanning@colostate.edu","phone":"970-491-3403","focus":"Oversees college development teams","src":"giving.colostate.edu","email_status":"confirmed","decile":9,"sent":"","replied":"","bounced":"","meeting":"","ostatus":"Not contacted"},{"school":"Colorado State University","unit":"Central","name":"Katie Brownlee","title":"AVP, Principal Gifts & Campaign Strategy, CSU Foundation","email":"Katie.Brownlee@colostate.edu","phone":"970-491-0556","focus":"Principal gifts and campaign strategy","src":"giving.colostate.edu","email_status":"confirmed","decile":9,"sent":"","replied":"","bounced":"","meeting":"","ostatus":"Not contacted"},{"school":"Colorado State University","unit":"Central","name":"Karen Dunbar","title":"AVP, Gift Planning, CSU Foundation","email":"Karen.Dunbar@colostate.edu","phone":"970-491-4254","focus":"Planned/estate giving","src":"giving.colostate.edu","email_status":"confirmed","decile":9,"sent":"","replied":"","bounced":"","meeting":"","ostatus":"Not contacted"},{"school":"Colorado State University","unit":"Central","name":"Greg Lewis","title":"Executive Director, Corporate Engagement & Partnerships","email":"G.Lewis@colostate.edu","phone":"970-491-7908","focus":"Corporate relations","src":"giving.colostate.edu","email_status":"confirmed","decile":9,"sent":"","replied":"","bounced":"","meeting":"","ostatus":"Not contacted"},{"school":"Colorado State University","unit":"Central","name":"Peter Hartman","title":"Director, Foundation Relations, CSU Foundation","email":"Peter.Hartman@colostate.edu","phone":"970-491-3251","focus":"Foundation relations","src":"giving.colostate.edu","email_status":"confirmed","decile":9,"sent":"","replied":"","bounced":"","meeting":"","ostatus":"Not contacted"},{"school":"Harvard University","unit":"Engineering","name":"Thomas J. Trapani","title":"Senior Director of Development, School of Engineering & Applied Sciences (SEAS)","email":"tom_trapani@harvard.edu","phone":"","focus":"Development lead – Engineering / Applied Sciences","src":"seas.harvard.edu","email_status":"confirmed","decile":9,"sent":"","replied":"","bounced":"","meeting":"","ostatus":"Not contacted"}]